LICENSE
MANIFEST.in
README.md
jupyter-graphql.json
setup.cfg
setup.py
ipygraphql/__init__.py
ipygraphql/_version.py
ipygraphql/graphiql.py
ipygraphql.egg-info/PKG-INFO
ipygraphql.egg-info/SOURCES.txt
ipygraphql.egg-info/dependency_links.txt
ipygraphql.egg-info/not-zip-safe
ipygraphql.egg-info/requires.txt
ipygraphql.egg-info/top_level.txt
ipygraphql/static/extension.js
ipygraphql/static/index.js
ipygraphql/static/index.js.map
js/jupyter-graphql-0.0.4.tgz